vcspack2011/__init__.py
vcspack2011/utils.py
vcspack2011-0.1.dist-info/LICENSE.txt
vcspack2011-0.1.dist-info/METADATA
vcspack2011-0.1.dist-info/WHEEL
vcspack2011-0.1.dist-info/top_level.txt
vcspack2011-0.1.dist-info/RECORD
