Metadata-Version: 2.1
Name: vcspack2011
Version: 0.1
Summary: vcspack utilities
Home-page: UNKNOWN
Author: yashraj.pal
Author-email: yashraj.pal@ignitarium.com
License: MIT
Platform: UNKNOWN
License-File: LICENSE.txt
